{
  "type": "minecraft:entity",
  "pools": [
    {
      "entries": [
        {
          "name": "minecraft:glowstone_dust",
          "type": "minecraft:item",
          "functions": [
            {
              "add": false,
              "count": {
                "max": 2.0,
                "min": 1.0,
                "type": "minecraft:uniform"
              },
              "function": "minecraft:set_count"
            },
            {
              "function": "minecraft:enchanted_count_increase",
              "enchantment": "minecraft:looting",
              "count": {
                "type": "minecraft:uniform",
                "min": 0.0,
                "max": 1.0
              }
            }
          ]
        },
        {
          "name": "minecraft:sugar",
          "type": "minecraft:item",
          "functions": [
            {
              "add": false,
              "count": {
                "max": 2.0,
                "min": 1.0,
                "type": "minecraft:uniform"
              },
              "function": "minecraft:set_count"
            },
            {
              "function": "minecraft:enchanted_count_increase",
              "enchantment": "minecraft:looting",
              "count": {
                "type": "minecraft:uniform",
                "min": 0.0,
                "max": 1.0
              }
            }
          ]
        },
        {
          "name": "minecraft:redstone",
          "type": "minecraft:item",
          "functions": [
            {
              "add": false,
              "count": {
                "max": 2.0,
                "min": 1.0,
                "type": "minecraft:uniform"
              },
              "function": "minecraft:set_count"
            },
            {
              "function": "minecraft:enchanted_count_increase",
              "enchantment": "minecraft:looting",
              "count": {
                "type": "minecraft:uniform",
                "min": 0.0,
                "max": 1.0
              }
            }
          ]
        },
        {
          "name": "minecraft:spider_eye",
          "type": "minecraft:item",
          "functions": [
            {
              "add": false,
              "count": {
                "max": 2.0,
                "min": 1.0,
                "type": "minecraft:uniform"
              },
              "function": "minecraft:set_count"
            },
            {
              "function": "minecraft:enchanted_count_increase",
              "enchantment": "minecraft:looting",
              "count": {
                "type": "minecraft:uniform",
                "min": 0.0,
                "max": 1.0
              }
            }
          ]
        },
        {
          "name": "minecraft:fermented_spider_eye",
          "type": "minecraft:item",
          "functions": [
            {
              "add": false,
              "count": {
                "max": 2.0,
                "min": 1.0,
                "type": "minecraft:uniform"
              },
              "function": "minecraft:set_count"
            },
            {
              "function": "minecraft:enchanted_count_increase",
              "enchantment": "minecraft:looting",
              "count": {
                "type": "minecraft:uniform",
                "min": 0.0,
                "max": 1.0
              }
            }
          ]
        },
        {
          "name": "minecraft:glass_bottle",
          "type": "minecraft:item",
          "functions": [
            {
              "add": false,
              "count": {
                "max": 2.0,
                "min": 1.0,
                "type": "minecraft:uniform"
              },
              "function": "minecraft:set_count"
            },
            {
              "function": "minecraft:enchanted_count_increase",
              "enchantment": "minecraft:looting",
              "count": {
                "type": "minecraft:uniform",
                "min": 0.0,
                "max": 1.0
              }
            }
          ]
        },
        {
          "name": "minecraft:gunpowder",
          "type": "minecraft:item",
          "functions": [
            {
              "add": false,
              "count": {
                "max": 2.0,
                "min": 1.0,
                "type": "minecraft:uniform"
              },
              "function": "minecraft:set_count"
            },
            {
              "function": "minecraft:enchanted_count_increase",
              "enchantment": "minecraft:looting",
              "count": {
                "type": "minecraft:uniform",
                "min": 0.0,
                "max": 1.0
              }
            }
          ]
        },
        {
          "name": "minecraft:blaze_powder",
          "type": "minecraft:item",
          "functions": [
            {
              "add": false,
              "count": {
                "max": 2.0,
                "min": 1.0,
                "type": "minecraft:uniform"
              },
              "function": "minecraft:set_count"
            },
            {
              "function": "minecraft:enchanted_count_increase",
              "enchantment": "minecraft:looting",
              "count": {
                "type": "minecraft:uniform",
                "min": 0.0,
                "max": 1.0
              }
            }
          ]
        },
        {
          "name": "minecraft:nether_wart",
          "type": "minecraft:item",
          "weight": 2,
          "functions": [
            {
              "add": false,
              "count": {
                "max": 2.0,
                "min": 1.0,
                "type": "minecraft:uniform"
              },
              "function": "minecraft:set_count"
            },
            {
              "function": "minecraft:enchanted_count_increase",
              "enchantment": "minecraft:looting",
              "count": {
                "type": "minecraft:uniform",
                "min": 0.0,
                "max": 1.0
              }
            }
          ]
        },
        {
          "name": "minecraft:stick",
          "type": "minecraft:item",
          "weight": 2,
          "functions": [
            {
              "add": false,
              "count": {
                "max": 2.0,
                "min": 1.0,
                "type": "minecraft:uniform"
              },
              "function": "minecraft:set_count"
            },
            {
              "function": "minecraft:enchanted_count_increase",
              "enchantment": "minecraft:looting",
              "count": {
                "type": "minecraft:uniform",
                "min": 0.0,
                "max": 1.0
              }
            }
          ]
        }
      ],
      "rolls": {
        "max": 3.0,
        "min": 1.0,
        "type": "minecraft:uniform"
      }
    },
    {
      "entries": [
        {
          "type": "minecraft:loot_table",
          "value": "minecraft_remade:entity/template/villager"
        }
      ],
      "rolls": 1.0
    }
  ],
  "random_sequence": "minecraft:entities/witch"
}